README.md
setup.py
bochica/__init__.py
bochica.egg-info/PKG-INFO
bochica.egg-info/SOURCES.txt
bochica.egg-info/dependency_links.txt
bochica.egg-info/entry_points.txt
bochica.egg-info/not-zip-safe
bochica.egg-info/requires.txt
bochica.egg-info/top_level.txt