Metadata-Version: 1.0
Name: bochica
Version: 2018.6.25.2115
Summary: GNU Privacy Guard encryption-decryption graphical user interface
Home-page: https://github.com/wdbm/bochica
Author: Will Breaden Madden
Author-email: wbm@protonmail.ch
License: GPLv3
Platform: UNKNOWN
